Workbook
Name aporte: Planilha1!$D$15
Name qtde_anos: Planilha1!$D$16

Sheet Planilha1
C1: Planilha De Investimentos em Fundos Imobiliários
C3: Configuração | I3: Distribuição Sugerida por Perfil
C4: Salário | D4: 1000 | I4: TIPO DE FII | J4: Sugerido (%) | K4: Sugerido (R$) | L4: Atual (%) | M4: Diferença (%)
C5: Porcentagem a Investir | D5: 0.3 | I5: Papel | J5: =VLOOKUP($D$8&"-"&I5,'Planilha Auxiliar'!A1:D19,4,FALSE) -> 0.5 | K5: =$D$7*J5 -> 150 | L5: =SUMIF(Tabela4[Tipo], $I5, Tabela4[Valor]) / $D$7 -> 0 | M5: =L5-J5 -> -0.5
C6: Rendimento Carteira | D6: 0.006 | I6: Tijolo | J6: =VLOOKUP($D$8&"-"&I6,'Planilha Auxiliar'!A2:D20,4,FALSE) -> 0.3 | K6: =$D$7*J6 -> 90 | L6: =SUMIF(Tabela4[Tipo], $I6, Tabela4[Valor]) / $D$7 -> 0 | M6: =L6-J6 -> -0.3
C7: Valor a Investir | D7: =D4*D5 -> 300 | I7: Híbridos | J7: =VLOOKUP($D$8&"-"&I7,'Planilha Auxiliar'!A3:D21,4,FALSE) -> 0.1 | K7: =$D$7*J7 -> 30 | L7: =SUMIF(Tabela4[Tipo], $I7, Tabela4[Valor]) / $D$7 -> 0 | M7: =L7-J7 -> -0.1
C8: Perfil | D8: Conservador | I8: FOFs | J8: =VLOOKUP($D$8&"-"&I8,'Planilha Auxiliar'!A4:D22,4,FALSE) -> 0.1 | K8: =$D$7*J8 -> 30 | L8: =SUMIF(Tabela4[Tipo], $I8, Tabela4[Valor]) / $D$7 -> 0 | M8: =L8-J8 -> -0.1
I9: Desenvolvimento | J9: =VLOOKUP($D$8&"-"&I9,'Planilha Auxiliar'!A5:D23,4,FALSE) -> 0 | K9: =$D$7*J9 -> 0 | L9: =SUMIF(Tabela4[Tipo], $I9, Tabela4[Valor]) / $D$7 -> 0 | M9: =L9-J9 -> 0
I10: Hotelarias | J10: =VLOOKUP($D$8&"-"&I10,'Planilha Auxiliar'!A6:D24,4,FALSE) -> 0 | K10: =$D$7*J10 -> 0 | L10: =SUMIF(Tabela4[Tipo], $I10, Tabela4[Valor]) / $D$7 -> 0 | M10: =L10-J10 -> 0
C14: Investimento Mensal | I14: Projeções | K14: Dividendos
C15: Quanto investir por mês? | D15: 1260 | I15: Quanto em 2 anos? | J15: =FV($D$17,$B23*12,$D$15*-1) -> 34306.81 | K15: =J15*$D$6 -> 205.84086
C16: Por quantos anos? | D16: 10 | I16: Quanto em 5 anos? | J16: =FV($D$17,$B24*12,$D$15*-1) -> 105558.91 | K16: =J16*$D$6 -> 633.35347
C17: Taxa de rendimento mensal? | D17: 0.01079 | I17: Quanto em 10 anos? | J17: =FV($D$17,$B25*12,$D$15*-1) -> 306538.11 | K17: =J17*$D$6 -> 1839.2286
C18: Patrimônio acumulado? | D18: =FV(D17,D16*12,D15*-1) -> 306538.11 | I18: Quanto em 20 anos? | J18: =FV($D$17,$B26*12,$D$15*-1) -> 1417750 | K18: =J18*$D$6 -> 8506.4999
C19: Dividendos mensais? | D19: =D18*D6 -> 1839.2286 | I19: Quanto em 30 anos? | J19: =FV($D$17,$B27*12,$D$15*-1) -> 5445933.8 | K19: =J19*$D$6 -> 32675.603
B23: 2 | I23: Fundos Registrados
B24: 5 | I24: Nome | J24: Tipo | K24: Valor
B25: 10
B26: 20
B27: 30

Sheet Planilha Auxiliar
A1: Chave | B1: Perfil | C1: Tipo de FII | D1: Percentual
A2: =B2&"-"&C2 -> Conservador-Papel | B2: Conservador | C2: Papel | D2: 0.5
A3: =B3&"-"&C3 -> Conservador-Tijolo | B3: Conservador | C3: Tijolo | D3: 0.3
A4: =B4&"-"&C4 -> Conservador-Híbridos | B4: Conservador | C4: Híbridos | D4: 0.1
A5: =B5&"-"&C5 -> Conservador-FOFs | B5: Conservador | C5: FOFs | D5: 0.1
A6: =B6&"-"&C6 -> Conservador-Desenvolvimento | B6: Conservador | C6: Desenvolvimento | D6: 0
A7: =B7&"-"&C7 -> Conservador-Hotelarias | B7: Conservador | C7: Hotelarias | D7: 0
A8: =B8&"-"&C8 -> Moderado-Papel | B8: Moderado | C8: Papel | D8: 0.4
A9: =B9&"-"&C9 -> Moderado-Tijolo | B9: Moderado | C9: Tijolo | D9: 0.35
A10: =B10&"-"&C10 -> Moderado-Híbridos | B10: Moderado | C10: Híbridos | D10: 0.1
A11: =B11&"-"&C11 -> Moderado-FOFs | B11: Moderado | C11: FOFs | D11: 0.05
A12: =B12&"-"&C12 -> Moderado-Desenvolvimento | B12: Moderado | C12: Desenvolvimento | D12: 0.05
A13: =B13&"-"&C13 -> Moderado-Hotelarias | B13: Moderado | C13: Hotelarias | D13: 0.05
... A19: =B19&"-"&C19 -> Agressivo-Hotelarias | B19: Agressivo | C19: Hotelarias | D19: 0.05
